password_permute.py
password_permute-0.2.dist-info/WHEEL
password_permute-0.2.dist-info/RECORD
password_permute-0.2.dist-info/METADATA
password_permute-0.2.dist-info/top_level.txt
password_permute-0.2.dist-info/DESCRIPTION.rst
password_permute-0.2.dist-info/metadata.json
password_permute-0.2.dist-info/entry_points.txt
