Metadata-Version: 2.0
Name: password-permute
Version: 0.2
Summary: Rearrange generated passwords so they're easier to type on a mobile device
Home-page: https://github.com/moreati/password-permute
Author: Alex Willmer
Author-email: alex@moreati.org.uk
License: UNKNOWN
Platform: UNKNOWN
Classifier: License :: OSI Approved :: BSD License
Classifier: Programming Language :: Python :: 2.6
Classifier: Programming Language :: Python :: 2.7
Classifier: Intended Audience :: Developers
Classifier: Topic :: Software Development :: Libraries :: Python Modules
Classifier: Topic :: Security
